python_colors/__init__.py
python_colors/cli.py
python_colors/colors.py
python_colors-0.1.2.dist-info/DESCRIPTION.rst
python_colors-0.1.2.dist-info/METADATA
python_colors-0.1.2.dist-info/RECORD
python_colors-0.1.2.dist-info/WHEEL
python_colors-0.1.2.dist-info/entry_points.txt
python_colors-0.1.2.dist-info/metadata.json
python_colors-0.1.2.dist-info/top_level.txt
