Metadata-Version: 2.0
Name: python-colors
Version: 0.1.2
Summary: Print colored text on UNIX terminals
Home-page: https://github.com/marbrb/python-colors
Author: Miguel Angel Rodriguez Bermudez
Author-email: marbrb1@gmail.com
License: GNU General Public License v3
Keywords: python_colors
Platform: UNKNOWN
Classifier: Development Status :: 2 - Pre-Alpha
Classifier: Intended Audience :: Developers
Classifier: License :: OSI Approved :: GNU General Public License v3 (GPLv3)
Classifier: Natural Language :: English
Classifier: Programming Language :: Python :: 2
Classifier: Programming Language :: Python :: 2.7
Classifier: Programming Language :: Python :: 3
Classifier: Programming Language :: Python :: 3.4
Classifier: Programming Language :: Python :: 3.5
Classifier: Programming Language :: Python :: 3.6
Requires-Dist: Click (>=6.0)
